wsssss/__init__.py
wsssss/functions.py
wsssss/load_data.py
wsssss/_bin/__init__.py
wsssss/_bin/check_grid.py
wsssss/_bin/mesa_go.py
wsssss/_bin/gyre_driver/INPUT_GYRE_4.4_ad.in
wsssss/_bin/gyre_driver/INPUT_GYRE_5.2_ad.in
wsssss/_bin/gyre_driver/INPUT_GYRE_6_ad.in
wsssss/_bin/gyre_driver/INPUT_GYRE_7_ad.in
wsssss/_bin/gyre_driver/INPUT_GYRE_8_ad.in
wsssss/_bin/gyre_driver/gyre_driver.py
wsssss/constants/__init__.py
wsssss/constants/post15140.py
wsssss/constants/pre15140.py
wsssss/inlists/__init__.py
wsssss/inlists/create_grid.py
wsssss/inlists/inlists.py
wsssss/plotting/__init__.py
wsssss/plotting/kipper.py
wsssss/plotting/plotting.py
wsssss/plotting/utils.py
wsssss-0.7.5.dist-info/licenses/LICENSE
wsssss-0.7.5.dist-info/METADATA
wsssss-0.7.5.dist-info/WHEEL
wsssss-0.7.5.dist-info/entry_points.txt
wsssss-0.7.5.dist-info/top_level.txt
wsssss-0.7.5.dist-info/RECORD
